{"widget_positions":{"wp_inactive_widgets":["media_image-3","tag_cloud-3","opus-blog-social-icons-4"],"sidebar-1":["woocommerce_products-2","woocommerce_top_rated_products-2","opus-blog-tabbed-3","opus-blog-post-slider-3","opus-blog-author-3","opus-blog-popular-post-widget-3","opus-blog-social-icons-3","opus-blog-featured-post-3","search-2","recent-posts-2","recent-comments-2","archives-2","categories-2","meta-2"],"left-sidebar":[],"footer-1":["text-3"],"footer-2":["opus-blog-featured-post-4"],"footer-3":["opus-blog-featured-post-5"],"footer-4":["media_gallery-3"],"array_version":3},"widget_options":{"media_image":{"_multiwidget":1,"3":[]},"tag_cloud":{"_multiwidget":1,"3":[]},"opus-blog-social-icons":{"_multiwidget":1,"3":{"title":"Follow Us"},"4":{"title":"hello"}},"woocommerce_products":{"2":{"title":"Products","number":5,"show":"","orderby":"date","order":"desc","hide_free":0,"show_hidden":0},"_multiwidget":1},"woocommerce_top_rated_products":{"2":{"title":"Top rated products","number":5},"_multiwidget":1},"opus-blog-tabbed":{"_multiwidget":1,"3":{"title":"Recent Post","popular_title":"Popular","recent_title":"Recent","commented_title":"Comment","post-number":3}},"opus-blog-post-slider":{"_multiwidget":1,"3":{"title":"Recent Posts","cat":26,"post-number":3}},"opus-blog-author":{"_multiwidget":1,"3":{"title":"About Me","author_description":"Aliquam sapien nulla, venenatis id finibus at, eleifend a turpis. Aliquam ac nibh id lorem ornare accumsan maximus at mauris.","author_image":"http:\/\/demo.akithemes.com\/opus-blog\/wp-content\/uploads\/sites\/4\/2019\/08\/author1.png","author_facebook":"#","author_twitter":"#","author_linkedin":"#","author_instagram":"#","author_pinterest":"#","author_youtube":"#","author_vk":"#","author_sign":"Richard"}},"opus-blog-popular-post-widget":{"_multiwidget":1,"3":{"title":"Latest Posts","order_by":"popular","count":"3"}},"opus-blog-featured-post":{"_multiwidget":1,"3":{"title":"Recent Posts","cat":26,"post-number":3},"4":{"title":"Recent Posts","cat":0,"post-number":3},"5":{"title":"Popular Posts","cat":0,"post-number":3}},"search":{"2":{"title":""},"_multiwidget":1},"recent-posts":{"2":{"title":"","number":5},"_multiwidget":1},"recent-comments":{"2":{"title":"","number":5},"_multiwidget":1},"archives":{"2":{"title":"","count":0,"dropdown":0},"_multiwidget":1},"categories":{"2":{"title":"","count":1,"hierarchical":0,"dropdown":0},"_multiwidget":1},"meta":{"2":{"title":""},"_multiwidget":1},"text":{"1":[],"_multiwidget":1,"3":{"title":"About Opus Blog","text":"Etiam nec purus urna. Integer dictum, arcu et fringilla facilisis, nunc enim suscipit mi, vel mattis leo urna a sem.\r\n\r\nAliquam sapien nulla, venenatis id finibus at, eleifend a turpis. Aliquam ac nibh id lorem ornare accumsan maximus at mauris.","filter":true,"visual":true}},"media_gallery":{"_multiwidget":1,"3":{"title":"Gallery","ids":[54,53,50,49,48,47,46,51,22],"columns":3,"size":"thumbnail","link_type":"post","orderby_random":false}}}}